yachain/__init__.py
yachain/config.py
yachain-0.1.4.dist-info/DESCRIPTION.rst
yachain-0.1.4.dist-info/METADATA
yachain-0.1.4.dist-info/RECORD
yachain-0.1.4.dist-info/WHEEL
yachain-0.1.4.dist-info/entry_points.txt
yachain-0.1.4.dist-info/metadata.json
yachain-0.1.4.dist-info/top_level.txt
