Metadata-Version: 2.0
Name: yachain
Version: 0.1.4
Summary: YAML parser
Home-page: http://github.com/hootnot/yachain
Author: F. Brekeveld
Author-email: f.brekeveld@gmail.com
License: MIT
Keywords: YAML parser configuration
Platform: UNKNOWN
Classifier: Programming Language :: Python
Classifier: License :: OSI Approved :: MIT License
Classifier: Intended Audience :: Developers
Classifier: Operating System :: OS Independent
Classifier: Development Status :: 5 - Production/Stable
Classifier: Topic :: Software Development :: Libraries :: Python Modules
Classifier: Programming Language :: Python
Classifier: Programming Language :: Python :: 2.7
Classifier: Programming Language :: Python :: 3.4
Classifier: Programming Language :: Python :: 3.5
Classifier: Programming Language :: Python :: 3.6
Classifier: Programming Language :: Python :: 3.7
